{"frameRate":24,"armature":[{"animation":[{"duration":0,"frame":[],"slot":[{"frame":[{"duration":0,"color":{},"tweenEasing":null}],"name":"else4"}],"ffd":[],"playTimes":0,"name":"idle_1","bone":[{"frame":[{"duration":0,"transform":{},"tweenEasing":null}],"name":"root"},{"frame":[{"duration":0,"transform":{"skX":21.275,"skY":21.275},"tweenEasing":null}],"name":"right leg"},{"frame":[{"duration":0,"transform":{"skX":-23.565,"skY":-23.565},"tweenEasing":null}],"name":"right l"},{"frame":[{"duration":0,"transform":{"skX":21.1234,"skY":21.1234},"tweenEasing":null}],"name":"left l"},{"frame":[{"duration":0,"transform":{"skX":-23.7209,"skY":-23.7209},"tweenEasing":null}],"name":"left leg"},{"frame":[{"duration":0,"transform":{"skX":-18.3828,"skY":-18.3828},"tweenEasing":null}],"name":"left arm"},{"frame":[{"duration":0,"transform":{},"tweenEasing":null}],"name":"neck"},{"frame":[{"duration":0,"transform":{"skX":1.6126,"skY":1.6126},"tweenEasing":null}],"name":"right arm"},{"frame":[{"duration":0,"transform":{"skX":65.3671,"skY":65.3671},"tweenEasing":null}],"name":"left a"},{"frame":[{"duration":0,"transform":{},"tweenEasing":null}],"name":"Head"},{"frame":[{"duration":0,"transform":{},"tweenEasing":null}],"name":"right a"},{"frame":[{"duration":0,"transform":{},"tweenEasing":null}],"name":"body"},{"frame":[{"duration":0,"transform":{},"tweenEasing":null}],"name":"bow"},{"frame":[{"duration":0,"transform":{"skX":23.7207,"skY":23.7207},"tweenEasing":null}],"name":"shoulder"}]},{"duration":0,"frame":[],"slot":[],"ffd":[],"name":"aimDown_1","bone":[{"frame":[{"duration":0,"transform":{"y":14.1607,"skX":-10.4096,"skY":-10.4096},"tweenEasing":null}],"name":"root"},{"frame":[{"duration":0,"transform":{"skX":18.2795,"skY":18.2795},"tweenEasing":null}],"name":"right leg"},{"frame":[{"duration":0,"transform":{"skX":-31.9979,"skY":-31.9979},"tweenEasing":null}],"name":"right l"},{"frame":[{"duration":0,"transform":{"skX":6.9856,"skY":6.9856},"tweenEasing":null}],"name":"left l"},{"frame":[{"duration":0,"transform":{"skX":-2.8724,"skY":-2.8724},"tweenEasing":null}],"name":"left leg"},{"frame":[{"duration":0,"transform":{"skX":55.3275,"skY":55.3275},"tweenEasing":null}],"name":"left arm"},{"frame":[{"duration":0,"transform":{},"tweenEasing":null}],"name":"neck"},{"frame":[{"duration":0,"transform":{"skX":-18.2809,"skY":-18.2809},"tweenEasing":null}],"name":"right arm"},{"frame":[{"duration":0,"transform":{"skX":-60.6812,"skY":-60.6812},"tweenEasing":null}],"name":"left a"},{"frame":[{"duration":0,"transform":{},"tweenEasing":null}],"name":"Head"},{"frame":[{"duration":0,"transform":{"skX":17.7842,"skY":17.7842},"tweenEasing":null}],"name":"right a"},{"frame":[{"duration":0,"transform":{"skX":20.8417,"skY":20.8417},"tweenEasing":null}],"name":"body"},{"frame":[{"duration":0,"transform":{"skX":7.2161,"skY":7.2161},"tweenEasing":null}],"name":"bow"},{"frame":[{"duration":0,"transform":{"skX":68.7891,"skY":68.7891},"tweenEasing":null}],"name":"shoulder"}]},{"duration":0,"frame":[],"slot":[],"ffd":[],"playTimes":0,"name":"idle_2","bone":[{"frame":[{"duration":0,"transform":{},"tweenEasing":null}],"name":"root"},{"frame":[{"duration":0,"transform":{"skX":22.8671,"skY":22.8671},"tweenEasing":null}],"name":"right leg"},{"frame":[{"duration":0,"transform":{"skX":-27.143,"skY":-27.143},"tweenEasing":null}],"name":"left leg"},{"frame":[{"duration":0,"transform":{},"tweenEasing":null}],"name":"body"},{"frame":[{"duration":0,"transform":{"skX":-22.3748,"skY":-22.3748},"tweenEasing":null}],"name":"right l"},{"frame":[{"duration":0,"transform":{"skX":21.1792,"skY":21.1792},"tweenEasing":null}],"name":"left l"},{"frame":[{"duration":0,"transform":{},"tweenEasing":null}],"name":"neck"},{"frame":[{"duration":0,"transform":{"skX":33.0963,"skY":33.0963},"tweenEasing":null}],"name":"right arm"},{"frame":[{"duration":0,"transform":{"skX":1.6661,"skY":1.6661},"tweenEasing":null}],"name":"left arm"},{"frame":[{"duration":0,"transform":{},"tweenEasing":null}],"name":"Head"},{"frame":[{"duration":0,"transform":{"skX":75.9225,"skY":75.9225},"tweenEasing":null}],"name":"left a"},{"frame":[{"duration":0,"transform":{"skX":22.918,"skY":22.918},"tweenEasing":null}],"name":"right a"},{"frame":[{"duration":0,"transform":{},"tweenEasing":null}],"name":"bow"},{"frame":[{"duration":0,"transform":{},"tweenEasing":null}],"name":"shoulder"}]},{"duration":6,"frame":[],"slot":[],"ffd":[],"playTimes":0,"name":"sit","bone":[{"frame":[{"duration":6,"transform":{},"tweenEasing":0},{"duration":0,"transform":{"y":65.5264},"tweenEasing":null}],"name":"root"},{"frame":[{"duration":6,"transform":{"skX":22.8671,"skY":22.8671},"tweenEasing":0},{"duration":0,"transform":{"skX":-40.0154,"skY":-40.0154},"tweenEasing":null}],"name":"right leg"},{"frame":[{"duration":6,"transform":{"skX":-27.143,"skY":-27.143},"tweenEasing":0},{"duration":0,"transform":{"skX":-56.4935,"skY":-56.4935},"tweenEasing":null}],"name":"left leg"},{"frame":[{"duration":6,"transform":{},"tweenEasing":0},{"duration":0,"transform":{"skX":48.0938,"skY":48.0938},"tweenEasing":null}],"name":"body"},{"frame":[{"duration":6,"transform":{"skX":-22.3748,"skY":-22.3748},"tweenEasing":0},{"duration":0,"transform":{"skX":47.0619,"skY":47.0619},"tweenEasing":null}],"name":"right l"},{"frame":[{"duration":6,"transform":{"skX":21.1792,"skY":21.1792},"tweenEasing":0},{"duration":0,"transform":{"skX":132.9069,"skY":132.9069},"tweenEasing":null}],"name":"left l"},{"frame":[{"duration":6,"transform":{},"tweenEasing":null}],"name":"neck"},{"frame":[{"duration":6,"transform":{"skX":33.0963,"skY":33.0963},"tweenEasing":0},{"duration":0,"transform":{"skX":20.2105,"skY":20.2105},"tweenEasing":null}],"name":"right arm"},{"frame":[{"duration":6,"transform":{"skX":1.6661,"skY":1.6661},"tweenEasing":0},{"duration":0,"transform":{"skX":-41.0415,"skY":-41.0415},"tweenEasing":null}],"name":"left arm"},{"frame":[{"duration":6,"transform":{},"tweenEasing":0},{"duration":0,"transform":{"y":3.7034,"x":12.8792},"tweenEasing":null}],"name":"Head"},{"frame":[{"duration":6,"transform":{"skX":75.9225,"skY":75.9225},"tweenEasing":0},{"duration":0,"transform":{"skX":5.1411,"skY":5.1411},"tweenEasing":null}],"name":"left a"},{"frame":[{"duration":6,"transform":{"skX":22.918,"skY":22.918},"tweenEasing":0},{"duration":0,"transform":{"skX":20.0268,"skY":20.0268},"tweenEasing":null}],"name":"right a"},{"frame":[{"duration":6,"transform":{},"tweenEasing":null}],"name":"bow"},{"frame":[{"duration":6,"transform":{},"tweenEasing":null}],"name":"shoulder"}]},{"duration":20,"frame":[],"slot":[],"ffd":[],"playTimes":0,"name":"walk","bone":[{"frame":[{"duration":20,"transform":{},"tweenEasing":null}],"name":"root"},{"frame":[{"duration":10,"transform":{"skX":9.1123,"skY":9.1123},"tweenEasing":0},{"duration":10,"transform":{"skX":73.6716,"skY":73.6716},"tweenEasing":0},{"duration":0,"transform":{"skX":9.1123,"skY":9.1123},"tweenEasing":null}],"name":"right leg"},{"frame":[{"duration":10,"transform":{"skX":-15.3634,"skY":-15.3634},"tweenEasing":0},{"duration":10,"transform":{"skX":-75.6626,"skY":-75.6626},"tweenEasing":0},{"duration":0,"transform":{"skX":-15.3634,"skY":-15.3634},"tweenEasing":null}],"name":"left leg"},{"frame":[{"duration":20,"transform":{},"tweenEasing":null}],"name":"body"},{"frame":[{"duration":10,"transform":{"skX":-5.3663,"skY":-5.3663},"tweenEasing":0},{"duration":10,"transform":{"skX":-25.1389,"skY":-25.1389},"tweenEasing":0},{"duration":0,"transform":{"skX":-5.3663,"skY":-5.3663},"tweenEasing":null}],"name":"right l"},{"frame":[{"duration":10,"transform":{"skX":51.2394,"skY":51.2394},"tweenEasing":0},{"duration":10,"transform":{"skX":78.1777,"skY":78.1777},"tweenEasing":0},{"duration":0,"transform":{"skX":51.2394,"skY":51.2394},"tweenEasing":null}],"name":"left l"},{"frame":[{"duration":20,"transform":{},"tweenEasing":null}],"name":"neck"},{"frame":[{"duration":10,"transform":{"skX":25.279,"skY":25.279},"tweenEasing":0},{"duration":10,"transform":{"skX":92.6168,"skY":92.6168},"tweenEasing":0},{"duration":0,"transform":{"skX":25.279,"skY":25.279},"tweenEasing":null}],"name":"right arm"},{"frame":[{"duration":10,"transform":{"skX":5.7784,"skY":5.7784},"tweenEasing":0},{"duration":10,"transform":{"skX":-73.1932,"skY":-73.1932},"tweenEasing":0},{"duration":0,"transform":{"skX":5.7784,"skY":5.7784},"tweenEasing":null}],"name":"left arm"},{"frame":[{"duration":20,"transform":{},"tweenEasing":null}],"name":"Head"},{"frame":[{"duration":10,"transform":{"skX":45.1473,"skY":45.1473},"tweenEasing":0},{"duration":10,"transform":{"skX":103.8181,"skY":103.8181},"tweenEasing":0},{"duration":0,"transform":{"skX":45.1473,"skY":45.1473},"tweenEasing":null}],"name":"left a"},{"frame":[{"duration":10,"transform":{"skX":22.918,"skY":22.918},"tweenEasing":0},{"duration":10,"transform":{"skX":-6.5995,"skY":-6.5995},"tweenEasing":0},{"duration":0,"transform":{"skX":22.918,"skY":22.918},"tweenEasing":null}],"name":"right a"},{"frame":[{"duration":20,"transform":{},"tweenEasing":null}],"name":"bow"},{"frame":[{"duration":20,"transform":{},"tweenEasing":null}],"name":"shoulder"}]},{"duration":0,"frame":[],"slot":[],"ffd":[],"playTimes":0,"name":"run_1","bone":[{"frame":[{"duration":0,"transform":{},"tweenEasing":null}],"name":"root"},{"frame":[{"duration":0,"transform":{"skX":22.8671,"skY":22.8671},"tweenEasing":null}],"name":"right leg"},{"frame":[{"duration":0,"transform":{"skX":-27.143,"skY":-27.143},"tweenEasing":null}],"name":"left leg"},{"frame":[{"duration":0,"transform":{},"tweenEasing":null}],"name":"body"},{"frame":[{"duration":0,"transform":{"skX":-22.3748,"skY":-22.3748},"tweenEasing":null}],"name":"right l"},{"frame":[{"duration":0,"transform":{"skX":21.1792,"skY":21.1792},"tweenEasing":null}],"name":"left l"},{"frame":[{"duration":0,"transform":{},"tweenEasing":null}],"name":"neck"},{"frame":[{"duration":0,"transform":{"skX":25.279,"skY":25.279},"tweenEasing":null}],"name":"right arm"},{"frame":[{"duration":0,"transform":{"skX":-25.878,"skY":-25.878},"tweenEasing":null}],"name":"left arm"},{"frame":[{"duration":0,"transform":{},"tweenEasing":null}],"name":"Head"},{"frame":[{"duration":0,"transform":{"skX":16.2686,"skY":16.2686},"tweenEasing":null}],"name":"left a"},{"frame":[{"duration":0,"transform":{"skX":22.918,"skY":22.918},"tweenEasing":null}],"name":"right a"},{"frame":[{"duration":0,"transform":{},"tweenEasing":null}],"name":"bow"},{"frame":[{"duration":0,"transform":{},"tweenEasing":null}],"name":"shoulder"}]},{"duration":8,"frame":[],"slot":[{"frame":[{"duration":8,"color":{},"tweenEasing":null}],"name":"else4"}],"ffd":[],"playTimes":0,"name":"aim_1","bone":[{"frame":[{"duration":8,"transform":{},"tweenEasing":0},{"duration":0,"transform":{"y":14.1607,"skX":-10.4096,"skY":-10.4096},"tweenEasing":null}],"name":"root"},{"frame":[{"duration":8,"transform":{"skX":21.275,"skY":21.275},"tweenEasing":0},{"duration":0,"transform":{"skX":18.2795,"skY":18.2795},"tweenEasing":null}],"name":"right leg"},{"frame":[{"duration":8,"transform":{"skX":-23.565,"skY":-23.565},"tweenEasing":0},{"duration":0,"transform":{"skX":-31.9979,"skY":-31.9979},"tweenEasing":null}],"name":"right l"},{"frame":[{"duration":8,"transform":{"skX":21.1234,"skY":21.1234},"tweenEasing":0},{"duration":0,"transform":{"skX":6.9856,"skY":6.9856},"tweenEasing":null}],"name":"left l"},{"frame":[{"duration":8,"transform":{"skX":-23.7209,"skY":-23.7209},"tweenEasing":0},{"duration":0,"transform":{"skX":-2.8724,"skY":-2.8724},"tweenEasing":null}],"name":"left leg"},{"frame":[{"duration":4,"transform":{"skX":-18.3828,"skY":-18.3828},"tweenEasing":0},{"duration":4,"transform":{"skX":-39.7551,"skY":-39.7551},"tweenEasing":0},{"duration":0,"transform":{"skX":55.3275,"skY":55.3275},"tweenEasing":null}],"name":"left arm"},{"frame":[{"duration":8,"transform":{},"tweenEasing":null}],"name":"neck"},{"frame":[{"duration":8,"transform":{"skX":1.6126,"skY":1.6126},"tweenEasing":0},{"duration":0,"transform":{"skX":-18.2809,"skY":-18.2809},"tweenEasing":null}],"name":"right arm"},{"frame":[{"duration":4,"transform":{"skX":65.3671,"skY":65.3671},"tweenEasing":0},{"duration":4,"transform":{"skX":8.0542,"skY":8.0542},"tweenEasing":0},{"duration":0,"transform":{"skX":-60.234,"skY":-60.234},"tweenEasing":null}],"name":"left a"},{"frame":[{"duration":8,"transform":{},"tweenEasing":null}],"name":"Head"},{"frame":[{"duration":8,"transform":{},"tweenEasing":0},{"duration":0,"transform":{"skX":17.0065,"skY":17.0065},"tweenEasing":null}],"name":"right a"},{"frame":[{"duration":8,"transform":{},"tweenEasing":null}],"name":"body"},{"frame":[{"duration":8,"transform":{},"tweenEasing":0},{"duration":0,"transform":{"skX":-1.7499,"skY":-1.7499},"tweenEasing":null}],"name":"bow"},{"frame":[{"duration":8,"transform":{"skX":23.7207,"skY":23.7207},"tweenEasing":0},{"duration":0,"transform":{"skX":-1.2091,"skY":-1.2091},"tweenEasing":null}],"name":"shoulder"}]},{"duration":0,"frame":[],"slot":[],"ffd":[],"name":"aimUp_1","bone":[{"frame":[{"duration":0,"transform":{"y":14.1607,"skX":-10.4096,"skY":-10.4096},"tweenEasing":null}],"name":"root"},{"frame":[{"duration":0,"transform":{"skX":18.2795,"skY":18.2795},"tweenEasing":null}],"name":"right leg"},{"frame":[{"duration":0,"transform":{"skX":-31.9979,"skY":-31.9979},"tweenEasing":null}],"name":"right l"},{"frame":[{"duration":0,"transform":{"skX":6.9856,"skY":6.9856},"tweenEasing":null}],"name":"left l"},{"frame":[{"duration":0,"transform":{"skX":-2.8724,"skY":-2.8724},"tweenEasing":null}],"name":"left leg"},{"frame":[{"duration":0,"transform":{"skX":55.3275,"skY":55.3275},"tweenEasing":null}],"name":"left arm"},{"frame":[{"duration":0,"transform":{},"tweenEasing":null}],"name":"neck"},{"frame":[{"duration":0,"transform":{"skX":-18.2809,"skY":-18.2809},"tweenEasing":null}],"name":"right arm"},{"frame":[{"duration":0,"transform":{"skX":-62.0299,"skY":-62.0299},"tweenEasing":null}],"name":"left a"},{"frame":[{"duration":0,"transform":{},"tweenEasing":null}],"name":"Head"},{"frame":[{"duration":0,"transform":{"skX":12.5175,"skY":12.5175},"tweenEasing":null}],"name":"right a"},{"frame":[{"duration":0,"transform":{},"tweenEasing":null}],"name":"body"},{"frame":[{"duration":0,"transform":{"skX":4.2067,"skY":4.2067},"tweenEasing":null}],"name":"bow"},{"frame":[{"duration":0,"transform":{"skX":-83.8784,"skY":-83.8784},"tweenEasing":null}],"name":"shoulder"}]},{"duration":24,"frame":[],"slot":[],"ffd":[],"playTimes":0,"name":"idle_3","bone":[{"frame":[{"duration":6,"transform":{},"tweenEasing":0},{"duration":6,"transform":{"x":-15.5547},"tweenEasing":0},{"duration":6,"transform":{},"tweenEasing":0},{"duration":6,"transform":{"y":-2.5925,"x":27.1716},"tweenEasing":0},{"duration":0,"transform":{},"tweenEasing":null}],"name":"root"},{"frame":[{"duration":6,"transform":{"skX":3.4676,"skY":3.4676},"tweenEasing":0},{"duration":6,"transform":{"skX":4.8784,"skY":4.8784},"tweenEasing":0},{"duration":6,"transform":{"skX":3.4676,"skY":3.4676},"tweenEasing":0},{"duration":6,"transform":{"skX":8.5584,"skY":8.5584},"tweenEasing":0},{"duration":0,"transform":{"skX":3.4676,"skY":3.4676},"tweenEasing":null}],"name":"right leg"},{"frame":[{"duration":6,"transform":{"skX":-8.7888,"skY":-8.7888},"tweenEasing":0},{"duration":6,"transform":{"skX":0.8731,"skY":0.8731},"tweenEasing":0},{"duration":6,"transform":{"skX":-8.7888,"skY":-8.7888},"tweenEasing":0},{"duration":6,"transform":{"skX":-11.6512,"skY":-11.6512},"tweenEasing":0},{"duration":0,"transform":{"skX":-8.7888,"skY":-8.7888},"tweenEasing":null}],"name":"left leg"},{"frame":[{"duration":24,"transform":{},"tweenEasing":null}],"name":"body"},{"frame":[{"duration":6,"transform":{"skX":-10.859,"skY":-10.859},"tweenEasing":0},{"duration":6,"transform":{"skX":-32.1507,"skY":-32.1507},"tweenEasing":0},{"duration":6,"transform":{"skX":-10.859,"skY":-10.859},"tweenEasing":0},{"duration":6,"transform":{"skX":5.9349,"skY":5.9349},"tweenEasing":0},{"duration":0,"transform":{"skX":-10.859,"skY":-10.859},"tweenEasing":null}],"name":"right l"},{"frame":[{"duration":6,"transform":{"skX":10.8815,"skY":10.8815},"tweenEasing":0},{"duration":6,"transform":{"skX":-17.6807,"skY":-17.6807},"tweenEasing":0},{"duration":6,"transform":{"skX":10.8815,"skY":10.8815},"tweenEasing":0},{"duration":6,"transform":{"skX":37.1779,"skY":37.1779},"tweenEasing":0},{"duration":0,"transform":{"skX":10.8815,"skY":10.8815},"tweenEasing":null}],"name":"left l"},{"frame":[{"duration":24,"transform":{},"tweenEasing":null}],"name":"neck"},{"frame":[{"duration":24,"transform":{},"tweenEasing":null}],"name":"shoulder"},{"frame":[{"duration":6,"transform":{"skX":10.0983,"skY":10.0983},"tweenEasing":0},{"duration":6,"transform":{"skX":3.1959,"skY":3.1959},"tweenEasing":0},{"duration":6,"transform":{"skX":10.0983,"skY":10.0983},"tweenEasing":0},{"duration":6,"transform":{"skX":27.7387,"skY":27.7387},"tweenEasing":0},{"duration":0,"transform":{"skX":10.0983,"skY":10.0983},"tweenEasing":null}],"name":"right arm"},{"frame":[{"duration":24,"transform":{},"tweenEasing":null}],"name":"Head"},{"frame":[{"duration":6,"transform":{},"tweenEasing":0},{"duration":6,"transform":{"skX":-13.2533,"skY":-13.2533},"tweenEasing":0},{"duration":6,"transform":{"skX":12.3106,"skY":12.3106},"tweenEasing":0},{"duration":6,"transform":{"skX":14.8753,"skY":14.8753},"tweenEasing":0},{"duration":0,"transform":{},"tweenEasing":null}],"name":"left arm"},{"frame":[{"duration":24,"transform":{},"tweenEasing":0},{"duration":0,"transform":{},"tweenEasing":null}],"name":"right a"},{"frame":[{"duration":6,"transform":{"skX":18.0412,"skY":18.0412},"tweenEasing":0},{"duration":6,"transform":{"skX":18.0412,"skY":18.0412},"tweenEasing":0},{"duration":6,"transform":{"skX":18.0412,"skY":18.0412},"tweenEasing":0},{"duration":6,"transform":{"skX":18.0412,"skY":18.0412},"tweenEasing":0},{"duration":0,"transform":{"skX":18.0412,"skY":18.0412},"tweenEasing":null}],"name":"left a"},{"frame":[{"duration":24,"transform":{},"tweenEasing":null}],"name":"bow"}]},{"duration":6,"frame":[],"slot":[],"ffd":[],"playTimes":0,"name":"up","bone":[{"frame":[{"duration":6,"transform":{"y":65.5264},"tweenEasing":0},{"duration":0,"transform":{},"tweenEasing":null}],"name":"root"},{"frame":[{"duration":6,"transform":{"skX":-40.0154,"skY":-40.0154},"tweenEasing":0},{"duration":0,"transform":{"skX":22.8671,"skY":22.8671},"tweenEasing":null}],"name":"right leg"},{"frame":[{"duration":6,"transform":{"skX":-56.4935,"skY":-56.4935},"tweenEasing":0},{"duration":0,"transform":{"skX":-27.143,"skY":-27.143},"tweenEasing":null}],"name":"left leg"},{"frame":[{"duration":6,"transform":{"skX":48.0938,"skY":48.0938},"tweenEasing":0},{"duration":0,"transform":{},"tweenEasing":null}],"name":"body"},{"frame":[{"duration":6,"transform":{"skX":47.0619,"skY":47.0619},"tweenEasing":0},{"duration":0,"transform":{"skX":-22.3748,"skY":-22.3748},"tweenEasing":null}],"name":"right l"},{"frame":[{"duration":6,"transform":{"skX":132.9069,"skY":132.9069},"tweenEasing":0},{"duration":0,"transform":{"skX":21.1792,"skY":21.1792},"tweenEasing":null}],"name":"left l"},{"frame":[{"duration":6,"transform":{},"tweenEasing":null}],"name":"neck"},{"frame":[{"duration":6,"transform":{"skX":20.2105,"skY":20.2105},"tweenEasing":0},{"duration":0,"transform":{"skX":33.0963,"skY":33.0963},"tweenEasing":null}],"name":"right arm"},{"frame":[{"duration":6,"transform":{"skX":-41.0415,"skY":-41.0415},"tweenEasing":0},{"duration":0,"transform":{"skX":1.6661,"skY":1.6661},"tweenEasing":null}],"name":"left arm"},{"frame":[{"duration":6,"transform":{"y":3.7034,"x":12.8792},"tweenEasing":0},{"duration":0,"transform":{},"tweenEasing":null}],"name":"Head"},{"frame":[{"duration":6,"transform":{"skX":5.1411,"skY":5.1411},"tweenEasing":0},{"duration":0,"transform":{"skX":75.9225,"skY":75.9225},"tweenEasing":null}],"name":"left a"},{"frame":[{"duration":6,"transform":{"skX":20.0268,"skY":20.0268},"tweenEasing":0},{"duration":0,"transform":{"skX":22.918,"skY":22.918},"tweenEasing":null}],"name":"right a"},{"frame":[{"duration":6,"transform":{},"tweenEasing":null}],"name":"bow"},{"frame":[{"duration":6,"transform":{},"tweenEasing":null}],"name":"shoulder"}]},{"duration":13,"frame":[],"slot":[],"ffd":[],"playTimes":0,"name":"hit_arm","bone":[{"frame":[{"duration":13,"transform":{},"tweenEasing":0},{"duration":0,"transform":{},"tweenEasing":null}],"name":"root"},{"frame":[{"duration":13,"transform":{"skX":3.4676,"skY":3.4676},"tweenEasing":0},{"duration":0,"transform":{"skX":3.4676,"skY":3.4676},"tweenEasing":null}],"name":"right leg"},{"frame":[{"duration":13,"transform":{"skX":-8.7888,"skY":-8.7888},"tweenEasing":0},{"duration":0,"transform":{"skX":-8.7888,"skY":-8.7888},"tweenEasing":null}],"name":"left leg"},{"frame":[{"duration":6,"transform":{},"tweenEasing":0},{"duration":7,"transform":{"skX":10.7533,"skY":10.7533},"tweenEasing":0},{"duration":0,"transform":{},"tweenEasing":null}],"name":"body"},{"frame":[{"duration":13,"transform":{"skX":-10.859,"skY":-10.859},"tweenEasing":0},{"duration":0,"transform":{"skX":-10.859,"skY":-10.859},"tweenEasing":null}],"name":"right l"},{"frame":[{"duration":13,"transform":{"skX":10.8815,"skY":10.8815},"tweenEasing":0},{"duration":0,"transform":{"skX":10.8815,"skY":10.8815},"tweenEasing":null}],"name":"left l"},{"frame":[{"duration":13,"transform":{},"tweenEasing":null}],"name":"neck"},{"frame":[{"duration":13,"transform":{},"tweenEasing":null}],"name":"shoulder"},{"frame":[{"duration":6,"transform":{"skX":10.0983,"skY":10.0983},"tweenEasing":0},{"duration":7,"transform":{"skX":-28.5992,"skY":-28.5992},"tweenEasing":0},{"duration":0,"transform":{"skX":10.0983,"skY":10.0983},"tweenEasing":null}],"name":"right arm"},{"frame":[{"duration":13,"transform":{},"tweenEasing":null}],"name":"Head"},{"frame":[{"duration":4,"transform":{},"tweenEasing":0},{"duration":2,"transform":{"skX":4.6364,"skY":4.6364},"tweenEasing":0},{"duration":7,"transform":{"skX":-78.0699,"skY":-78.0699},"tweenEasing":0},{"duration":0,"transform":{},"tweenEasing":null}],"name":"left arm"},{"frame":[{"duration":6,"transform":{},"tweenEasing":0},{"duration":7,"transform":{"skX":-64.7731,"skY":-64.7731},"tweenEasing":0},{"duration":0,"transform":{},"tweenEasing":null}],"name":"right a"},{"frame":[{"duration":6,"transform":{"skX":18.0412,"skY":18.0412},"tweenEasing":0},{"duration":7,"transform":{"skX":53.3765,"skY":53.3765},"tweenEasing":0},{"duration":0,"transform":{"skX":18.0412,"skY":18.0412},"tweenEasing":null}],"name":"left a"},{"frame":[{"duration":13,"transform":{},"tweenEasing":null}],"name":"bow"}]},{"duration":14,"frame":[],"slot":[],"ffd":[],"playTimes":0,"name":"hit_leg","bone":[{"frame":[{"duration":7,"transform":{},"tweenEasing":0},{"duration":7,"transform":{"skX":-0.0503,"skY":-0.0503,"x":30.4631},"tweenEasing":0},{"duration":0,"transform":{},"tweenEasing":null}],"name":"root"},{"frame":[{"duration":7,"transform":{"skX":3.4676,"skY":3.4676},"tweenEasing":0},{"duration":7,"transform":{"skX":28.1488,"skY":28.1488},"tweenEasing":0},{"duration":0,"transform":{"skX":3.4676,"skY":3.4676},"tweenEasing":null}],"name":"right leg"},{"frame":[{"duration":7,"transform":{"skX":-8.7888,"skY":-8.7888},"tweenEasing":0},{"duration":7,"transform":{"skX":-157.9708,"skY":-157.9708},"tweenEasing":0},{"duration":0,"transform":{"skX":-8.7888,"skY":-8.7888},"tweenEasing":null}],"name":"left leg"},{"frame":[{"duration":7,"transform":{},"tweenEasing":0},{"duration":7,"transform":{"skX":-16.2767,"skY":-16.2767},"tweenEasing":0},{"duration":0,"transform":{},"tweenEasing":null}],"name":"body"},{"frame":[{"duration":7,"transform":{"skX":-10.859,"skY":-10.859},"tweenEasing":0},{"duration":7,"transform":{"skX":-34.8962,"skY":-34.8962},"tweenEasing":0},{"duration":0,"transform":{"skX":-10.859,"skY":-10.859},"tweenEasing":null}],"name":"right l"},{"frame":[{"duration":4,"transform":{"skX":10.8815,"skY":10.8815},"tweenEasing":0},{"duration":3,"transform":{"skX":105.6561,"skY":105.6561},"tweenEasing":0},{"duration":3,"transform":{"skX":37.8342,"skY":37.8342},"tweenEasing":0},{"duration":4,"transform":{"skX":105.6561,"skY":105.6561},"tweenEasing":0},{"duration":0,"transform":{"skX":10.8815,"skY":10.8815},"tweenEasing":null}],"name":"left l"},{"frame":[{"duration":14,"transform":{},"tweenEasing":null}],"name":"neck"},{"frame":[{"duration":14,"transform":{},"tweenEasing":null}],"name":"shoulder"},{"frame":[{"duration":7,"transform":{"skX":10.0983,"skY":10.0983},"tweenEasing":0},{"duration":7,"transform":{"skX":27.3971,"skY":27.3971},"tweenEasing":0},{"duration":0,"transform":{"skX":10.0983,"skY":10.0983},"tweenEasing":null}],"name":"right arm"},{"frame":[{"duration":14,"transform":{},"tweenEasing":null}],"name":"Head"},{"frame":[{"duration":7,"transform":{},"tweenEasing":0},{"duration":7,"transform":{"skX":37.1328,"skY":37.1328},"tweenEasing":0},{"duration":0,"transform":{},"tweenEasing":null}],"name":"left arm"},{"frame":[{"duration":7,"transform":{},"tweenEasing":0},{"duration":7,"transform":{"skX":-68.2022,"skY":-68.2022},"tweenEasing":0},{"duration":0,"transform":{},"tweenEasing":null}],"name":"right a"},{"frame":[{"duration":7,"transform":{"skX":18.0412,"skY":18.0412},"tweenEasing":0},{"duration":7,"transform":{"skX":62.6289,"skY":62.6289},"tweenEasing":0},{"duration":0,"transform":{"skX":18.0412,"skY":18.0412},"tweenEasing":null}],"name":"left a"},{"frame":[{"duration":14,"transform":{},"tweenEasing":null}],"name":"bow"}]},{"duration":16,"frame":[],"slot":[],"ffd":[],"playTimes":0,"name":"hit_head","bone":[{"frame":[{"duration":8,"transform":{},"tweenEasing":0},{"duration":8,"transform":{},"tweenEasing":0},{"duration":0,"transform":{},"tweenEasing":null}],"name":"root"},{"frame":[{"duration":8,"transform":{"skX":3.4676,"skY":3.4676},"tweenEasing":0},{"duration":8,"transform":{"skX":3.4676,"skY":3.4676},"tweenEasing":0},{"duration":0,"transform":{"skX":3.4676,"skY":3.4676},"tweenEasing":null}],"name":"right leg"},{"frame":[{"duration":8,"transform":{"skX":-8.7888,"skY":-8.7888},"tweenEasing":0},{"duration":8,"transform":{"skX":-8.7888,"skY":-8.7888},"tweenEasing":0},{"duration":0,"transform":{"skX":-8.7888,"skY":-8.7888},"tweenEasing":null}],"name":"left leg"},{"frame":[{"duration":4,"transform":{},"tweenEasing":0},{"duration":4,"transform":{"skX":6.137,"skY":6.137},"tweenEasing":0},{"duration":8,"transform":{"skX":25.544,"skY":25.544},"tweenEasing":0},{"duration":0,"transform":{},"tweenEasing":null}],"name":"body"},{"frame":[{"duration":8,"transform":{"skX":-10.859,"skY":-10.859},"tweenEasing":0},{"duration":8,"transform":{"skX":-10.859,"skY":-10.859},"tweenEasing":0},{"duration":0,"transform":{"skX":-10.859,"skY":-10.859},"tweenEasing":null}],"name":"right l"},{"frame":[{"duration":8,"transform":{"skX":10.8815,"skY":10.8815},"tweenEasing":0},{"duration":8,"transform":{"skX":10.8815,"skY":10.8815},"tweenEasing":0},{"duration":0,"transform":{"skX":10.8815,"skY":10.8815},"tweenEasing":null}],"name":"left l"},{"frame":[{"duration":16,"transform":{},"tweenEasing":null}],"name":"neck"},{"frame":[{"duration":16,"transform":{},"tweenEasing":null}],"name":"shoulder"},{"frame":[{"duration":8,"transform":{"skX":10.0983,"skY":10.0983},"tweenEasing":0},{"duration":8,"transform":{"skX":75.8287,"skY":75.8287},"tweenEasing":0},{"duration":0,"transform":{"skX":10.0983,"skY":10.0983},"tweenEasing":null}],"name":"right arm"},{"frame":[{"duration":16,"transform":{},"tweenEasing":null}],"name":"Head"},{"frame":[{"duration":8,"transform":{},"tweenEasing":0},{"duration":8,"transform":{"skX":23.7721,"skY":23.7721},"tweenEasing":0},{"duration":0,"transform":{},"tweenEasing":null}],"name":"left arm"},{"frame":[{"duration":8,"transform":{},"tweenEasing":0},{"duration":8,"transform":{"skX":20.5491,"skY":20.5491},"tweenEasing":0},{"duration":0,"transform":{},"tweenEasing":null}],"name":"right a"},{"frame":[{"duration":8,"transform":{"skX":18.0412,"skY":18.0412},"tweenEasing":0},{"duration":8,"transform":{"skX":106.4367,"skY":106.4367},"tweenEasing":0},{"duration":0,"transform":{"skX":18.0412,"skY":18.0412},"tweenEasing":null}],"name":"left a"},{"frame":[{"duration":16,"transform":{},"tweenEasing":null}],"name":"bow"}]},{"duration":26,"frame":[],"slot":[],"ffd":[],"playTimes":0,"name":"hit_in_jump","bone":[{"frame":[{"duration":2,"transform":{},"tweenEasing":0},{"duration":7,"transform":{"y":-2.9204},"tweenEasing":0},{"duration":3,"transform":{"y":-166.6094},"tweenEasing":0},{"duration":12,"transform":{"y":-166.6094},"tweenEasing":0},{"duration":2,"transform":{"y":6.8943},"tweenEasing":0},{"duration":0,"transform":{},"tweenEasing":null}],"name":"root"},{"frame":[{"duration":5,"transform":{"skX":3.4676,"skY":3.4676},"tweenEasing":0},{"duration":4,"transform":{"skX":7.181,"skY":7.181},"tweenEasing":0},{"duration":3,"transform":{"skX":17.2437,"skY":17.2437},"tweenEasing":0},{"duration":4,"transform":{"skX":-40.9986,"skY":-40.9986},"tweenEasing":0},{"duration":8,"transform":{"skX":30.5834,"skY":30.5834},"tweenEasing":0},{"duration":2,"transform":{"skX":-1.8607,"skY":-1.8607},"tweenEasing":0},{"duration":0,"transform":{"skX":3.4676,"skY":3.4676},"tweenEasing":null}],"name":"right leg"},{"frame":[{"duration":5,"transform":{"skX":-8.7888,"skY":-8.7888},"tweenEasing":0},{"duration":7,"transform":{"skX":-29.5865,"skY":-29.5865},"tweenEasing":0},{"duration":4,"transform":{"skX":-20.8191,"skY":-20.8191},"tweenEasing":0},{"duration":8,"transform":{"skX":-139.0687,"skY":-139.0687},"tweenEasing":0},{"duration":2,"transform":{"skX":-4.8325,"skY":-4.8325},"tweenEasing":0},{"duration":0,"transform":{"skX":-8.7888,"skY":-8.7888},"tweenEasing":null}],"name":"left leg"},{"frame":[{"duration":2,"transform":{},"tweenEasing":0},{"duration":8,"transform":{"skX":9.4874,"skY":9.4874},"tweenEasing":0},{"duration":16,"transform":{"skX":12.885,"skY":12.885},"tweenEasing":0},{"duration":0,"transform":{},"tweenEasing":null}],"name":"body"},{"frame":[{"duration":2,"transform":{"skX":-10.859,"skY":-10.859},"tweenEasing":0},{"duration":10,"transform":{"skX":21.1631,"skY":21.1631},"tweenEasing":0},{"duration":14,"transform":{"skX":-28.8537,"skY":-28.8537},"tweenEasing":0},{"duration":0,"transform":{"skX":-10.859,"skY":-10.859},"tweenEasing":null}],"name":"right l"},{"frame":[{"duration":2,"transform":{"skX":10.8815,"skY":10.8815},"tweenEasing":0},{"duration":3,"transform":{"skX":-21.7855,"skY":-21.7855},"tweenEasing":0},{"duration":7,"transform":{"skX":22.7525,"skY":22.7525},"tweenEasing":0},{"duration":4,"transform":{"skX":65.0591,"skY":65.0591},"tweenEasing":0},{"duration":8,"transform":{"skX":63.1709,"skY":63.1709},"tweenEasing":0},{"duration":2,"transform":{"skX":4.9307,"skY":4.9307},"tweenEasing":0},{"duration":0,"transform":{"skX":10.8815,"skY":10.8815},"tweenEasing":null}],"name":"left l"},{"frame":[{"duration":26,"transform":{},"tweenEasing":null}],"name":"neck"},{"frame":[{"duration":26,"transform":{},"tweenEasing":null}],"name":"shoulder"},{"frame":[{"duration":2,"transform":{"skX":10.0983,"skY":10.0983},"tweenEasing":0},{"duration":3,"transform":{"skX":32.5741,"skY":32.5741},"tweenEasing":0},{"duration":7,"transform":{"skX":30.5516,"skY":30.5516},"tweenEasing":0},{"duration":4,"transform":{"skX":20.3357,"skY":20.3357},"tweenEasing":0},{"duration":10,"transform":{"skX":-22.8349,"skY":-22.8349},"tweenEasing":0},{"duration":0,"transform":{"skX":10.0983,"skY":10.0983},"tweenEasing":null}],"name":"right arm"},{"frame":[{"duration":26,"transform":{},"tweenEasing":null}],"name":"Head"},{"frame":[{"duration":5,"transform":{},"tweenEasing":0},{"duration":11,"transform":{"skX":-6.8892,"skY":-6.8892},"tweenEasing":0},{"duration":10,"transform":{"skX":-88.2519,"skY":-88.2519},"tweenEasing":0},{"duration":0,"transform":{},"tweenEasing":null}],"name":"left arm"},{"frame":[{"duration":2,"transform":{},"tweenEasing":0},{"duration":3,"transform":{"skX":21.764,"skY":21.764},"tweenEasing":0},{"duration":7,"transform":{"scX":0.9102,"scY":0.9102,"skX":43.3346,"skY":43.3346},"tweenEasing":0},{"duration":14,"transform":{"skX":-89.3315,"skY":-89.3315},"tweenEasing":0},{"duration":0,"transform":{},"tweenEasing":null}],"name":"right a"},{"frame":[{"duration":2,"transform":{"skX":18.0412,"skY":18.0412},"tweenEasing":0},{"duration":3,"transform":{"skX":73.1739,"skY":73.1739},"tweenEasing":0},{"duration":7,"transform":{"skX":85.5647,"skY":85.5647},"tweenEasing":0},{"duration":14,"transform":{"skX":-36.4645,"skY":-36.4645},"tweenEasing":0},{"duration":0,"transform":{"skX":18.0412,"skY":18.0412},"tweenEasing":null}],"name":"left a"},{"frame":[{"duration":26,"transform":{},"tweenEasing":null}],"name":"bow"}]},{"duration":24,"frame":[],"slot":[],"ffd":[],"playTimes":0,"name":"hit_arm_seq","bone":[{"frame":[{"duration":24,"transform":{},"tweenEasing":0},{"duration":0,"transform":{},"tweenEasing":null}],"name":"root"},{"frame":[{"duration":24,"transform":{"skX":3.4676,"skY":3.4676},"tweenEasing":0},{"duration":0,"transform":{"skX":3.4676,"skY":3.4676},"tweenEasing":null}],"name":"right leg"},{"frame":[{"duration":24,"transform":{"skX":-8.7888,"skY":-8.7888},"tweenEasing":0},{"duration":0,"transform":{"skX":-8.7888,"skY":-8.7888},"tweenEasing":null}],"name":"left leg"},{"frame":[{"duration":5,"transform":{},"tweenEasing":0},{"duration":1,"transform":{"skX":-6.2857,"skY":-6.2857},"tweenEasing":0},{"duration":18,"transform":{"skX":15.3233,"skY":15.3233},"tweenEasing":0},{"duration":0,"transform":{},"tweenEasing":null}],"name":"body"},{"frame":[{"duration":24,"transform":{"skX":-10.859,"skY":-10.859},"tweenEasing":0},{"duration":0,"transform":{"skX":-10.859,"skY":-10.859},"tweenEasing":null}],"name":"right l"},{"frame":[{"duration":24,"transform":{"skX":10.8815,"skY":10.8815},"tweenEasing":0},{"duration":0,"transform":{"skX":10.8815,"skY":10.8815},"tweenEasing":null}],"name":"left l"},{"frame":[{"duration":24,"transform":{},"tweenEasing":null}],"name":"neck"},{"frame":[{"duration":24,"transform":{},"tweenEasing":null}],"name":"shoulder"},{"frame":[{"duration":6,"transform":{"skX":10.0983,"skY":10.0983},"tweenEasing":0},{"duration":6,"transform":{"skX":-47.2641,"skY":-47.2641},"tweenEasing":0},{"duration":6,"transform":{"skX":34.4145,"skY":34.4145},"tweenEasing":0},{"duration":6,"transform":{"skX":-20.5169,"skY":-20.5169},"tweenEasing":0},{"duration":0,"transform":{"skX":10.0983,"skY":10.0983},"tweenEasing":null}],"name":"right arm"},{"frame":[{"duration":24,"transform":{},"tweenEasing":null}],"name":"Head"},{"frame":[{"duration":12,"transform":{},"tweenEasing":0},{"duration":6,"transform":{"skX":-120.598,"skY":-120.598},"tweenEasing":0},{"duration":6,"transform":{"skX":43.068,"skY":43.068},"tweenEasing":0},{"duration":0,"transform":{},"tweenEasing":null}],"name":"left arm"},{"frame":[{"duration":5,"transform":{},"tweenEasing":0},{"duration":1,"transform":{"skX":23.0727,"skY":23.0727},"tweenEasing":0},{"duration":6,"transform":{"skX":21.0873,"skY":21.0873},"tweenEasing":0},{"duration":6,"transform":{"skX":-48.7722,"skY":-48.7722},"tweenEasing":0},{"duration":6,"transform":{"skX":16.8012,"skY":16.8012},"tweenEasing":0},{"duration":0,"transform":{},"tweenEasing":null}],"name":"right a"},{"frame":[{"duration":24,"transform":{"skX":18.0412,"skY":18.0412},"tweenEasing":0},{"duration":0,"transform":{"skX":18.0412,"skY":18.0412},"tweenEasing":null}],"name":"left a"},{"frame":[{"duration":24,"transform":{},"tweenEasing":null}],"name":"bow"}]},{"duration":26,"frame":[],"slot":[],"ffd":[],"playTimes":0,"name":"hit_leg_seq","bone":[{"frame":[{"duration":26,"transform":{},"tweenEasing":0},{"duration":0,"transform":{},"tweenEasing":null}],"name":"root"},{"frame":[{"duration":26,"transform":{"skX":3.4676,"skY":3.4676},"tweenEasing":0},{"duration":0,"transform":{"skX":3.4676,"skY":3.4676},"tweenEasing":null}],"name":"right leg"},{"frame":[{"duration":26,"transform":{"skX":-8.7888,"skY":-8.7888},"tweenEasing":0},{"duration":0,"transform":{"skX":-8.7888,"skY":-8.7888},"tweenEasing":null}],"name":"left leg"},{"frame":[{"duration":26,"transform":{},"tweenEasing":0},{"duration":0,"transform":{},"tweenEasing":null}],"name":"body"},{"frame":[{"duration":26,"transform":{"skX":-10.859,"skY":-10.859},"tweenEasing":0},{"duration":0,"transform":{"skX":-10.859,"skY":-10.859},"tweenEasing":null}],"name":"right l"},{"frame":[{"duration":26,"transform":{"skX":10.8815,"skY":10.8815},"tweenEasing":0},{"duration":0,"transform":{"skX":10.8815,"skY":10.8815},"tweenEasing":null}],"name":"left l"},{"frame":[{"duration":26,"transform":{},"tweenEasing":null}],"name":"neck"},{"frame":[{"duration":26,"transform":{},"tweenEasing":null}],"name":"shoulder"},{"frame":[{"duration":26,"transform":{"skX":10.0983,"skY":10.0983},"tweenEasing":0},{"duration":0,"transform":{"skX":10.0983,"skY":10.0983},"tweenEasing":null}],"name":"right arm"},{"frame":[{"duration":26,"transform":{},"tweenEasing":null}],"name":"Head"},{"frame":[{"duration":26,"transform":{},"tweenEasing":0},{"duration":0,"transform":{},"tweenEasing":null}],"name":"left arm"},{"frame":[{"duration":26,"transform":{},"tweenEasing":0},{"duration":0,"transform":{},"tweenEasing":null}],"name":"right a"},{"frame":[{"duration":26,"transform":{"skX":18.0412,"skY":18.0412},"tweenEasing":0},{"duration":0,"transform":{"skX":18.0412,"skY":18.0412},"tweenEasing":null}],"name":"left a"},{"frame":[{"duration":26,"transform":{},"tweenEasing":null}],"name":"bow"}]},{"duration":24,"frame":[],"slot":[],"ffd":[],"playTimes":0,"name":"hit_mix_seq_1","bone":[{"frame":[{"duration":24,"transform":{},"tweenEasing":0},{"duration":0,"transform":{},"tweenEasing":null}],"name":"root"},{"frame":[{"duration":24,"transform":{"skX":3.4676,"skY":3.4676},"tweenEasing":0},{"duration":0,"transform":{"skX":3.4676,"skY":3.4676},"tweenEasing":null}],"name":"right leg"},{"frame":[{"duration":24,"transform":{"skX":-8.7888,"skY":-8.7888},"tweenEasing":0},{"duration":0,"transform":{"skX":-8.7888,"skY":-8.7888},"tweenEasing":null}],"name":"left leg"},{"frame":[{"duration":5,"transform":{},"tweenEasing":0},{"duration":1,"transform":{"skX":-6.2857,"skY":-6.2857},"tweenEasing":0},{"duration":18,"transform":{"skX":15.3233,"skY":15.3233},"tweenEasing":0},{"duration":0,"transform":{},"tweenEasing":null}],"name":"body"},{"frame":[{"duration":24,"transform":{"skX":-10.859,"skY":-10.859},"tweenEasing":0},{"duration":0,"transform":{"skX":-10.859,"skY":-10.859},"tweenEasing":null}],"name":"right l"},{"frame":[{"duration":24,"transform":{"skX":10.8815,"skY":10.8815},"tweenEasing":0},{"duration":0,"transform":{"skX":10.8815,"skY":10.8815},"tweenEasing":null}],"name":"left l"},{"frame":[{"duration":24,"transform":{},"tweenEasing":null}],"name":"neck"},{"frame":[{"duration":24,"transform":{},"tweenEasing":null}],"name":"shoulder"},{"frame":[{"duration":6,"transform":{"skX":10.0983,"skY":10.0983},"tweenEasing":0},{"duration":6,"transform":{"skX":-47.2641,"skY":-47.2641},"tweenEasing":0},{"duration":6,"transform":{"skX":34.4145,"skY":34.4145},"tweenEasing":0},{"duration":6,"transform":{"skX":-20.5169,"skY":-20.5169},"tweenEasing":0},{"duration":0,"transform":{"skX":10.0983,"skY":10.0983},"tweenEasing":null}],"name":"right arm"},{"frame":[{"duration":24,"transform":{},"tweenEasing":null}],"name":"Head"},{"frame":[{"duration":12,"transform":{},"tweenEasing":0},{"duration":6,"transform":{"skX":-120.598,"skY":-120.598},"tweenEasing":0},{"duration":6,"transform":{"skX":43.068,"skY":43.068},"tweenEasing":0},{"duration":0,"transform":{},"tweenEasing":null}],"name":"left arm"},{"frame":[{"duration":5,"transform":{},"tweenEasing":0},{"duration":1,"transform":{"skX":23.0727,"skY":23.0727},"tweenEasing":0},{"duration":6,"transform":{"skX":21.0873,"skY":21.0873},"tweenEasing":0},{"duration":6,"transform":{"skX":-48.7722,"skY":-48.7722},"tweenEasing":0},{"duration":6,"transform":{"skX":16.8012,"skY":16.8012},"tweenEasing":0},{"duration":0,"transform":{},"tweenEasing":null}],"name":"right a"},{"frame":[{"duration":24,"transform":{"skX":18.0412,"skY":18.0412},"tweenEasing":0},{"duration":0,"transform":{"skX":18.0412,"skY":18.0412},"tweenEasing":null}],"name":"left a"},{"frame":[{"duration":24,"transform":{},"tweenEasing":null}],"name":"bow"}]},{"duration":24,"frame":[],"slot":[],"ffd":[],"playTimes":0,"name":"hit_mix_seq_2","bone":[{"frame":[{"duration":24,"transform":{},"tweenEasing":0},{"duration":0,"transform":{},"tweenEasing":null}],"name":"root"},{"frame":[{"duration":24,"transform":{"skX":3.4676,"skY":3.4676},"tweenEasing":0},{"duration":0,"transform":{"skX":3.4676,"skY":3.4676},"tweenEasing":null}],"name":"right leg"},{"frame":[{"duration":24,"transform":{"skX":-8.7888,"skY":-8.7888},"tweenEasing":0},{"duration":0,"transform":{"skX":-8.7888,"skY":-8.7888},"tweenEasing":null}],"name":"left leg"},{"frame":[{"duration":5,"transform":{},"tweenEasing":0},{"duration":1,"transform":{"skX":-6.2857,"skY":-6.2857},"tweenEasing":0},{"duration":18,"transform":{"skX":15.3233,"skY":15.3233},"tweenEasing":0},{"duration":0,"transform":{},"tweenEasing":null}],"name":"body"},{"frame":[{"duration":24,"transform":{"skX":-10.859,"skY":-10.859},"tweenEasing":0},{"duration":0,"transform":{"skX":-10.859,"skY":-10.859},"tweenEasing":null}],"name":"right l"},{"frame":[{"duration":24,"transform":{"skX":10.8815,"skY":10.8815},"tweenEasing":0},{"duration":0,"transform":{"skX":10.8815,"skY":10.8815},"tweenEasing":null}],"name":"left l"},{"frame":[{"duration":24,"transform":{},"tweenEasing":null}],"name":"neck"},{"frame":[{"duration":24,"transform":{},"tweenEasing":null}],"name":"shoulder"},{"frame":[{"duration":6,"transform":{"skX":10.0983,"skY":10.0983},"tweenEasing":0},{"duration":6,"transform":{"skX":-47.2641,"skY":-47.2641},"tweenEasing":0},{"duration":6,"transform":{"skX":34.4145,"skY":34.4145},"tweenEasing":0},{"duration":6,"transform":{"skX":-20.5169,"skY":-20.5169},"tweenEasing":0},{"duration":0,"transform":{"skX":10.0983,"skY":10.0983},"tweenEasing":null}],"name":"right arm"},{"frame":[{"duration":24,"transform":{},"tweenEasing":null}],"name":"Head"},{"frame":[{"duration":12,"transform":{},"tweenEasing":0},{"duration":6,"transform":{"skX":-120.598,"skY":-120.598},"tweenEasing":0},{"duration":6,"transform":{"skX":43.068,"skY":43.068},"tweenEasing":0},{"duration":0,"transform":{},"tweenEasing":null}],"name":"left arm"},{"frame":[{"duration":5,"transform":{},"tweenEasing":0},{"duration":1,"transform":{"skX":23.0727,"skY":23.0727},"tweenEasing":0},{"duration":6,"transform":{"skX":21.0873,"skY":21.0873},"tweenEasing":0},{"duration":6,"transform":{"skX":-48.7722,"skY":-48.7722},"tweenEasing":0},{"duration":6,"transform":{"skX":16.8012,"skY":16.8012},"tweenEasing":0},{"duration":0,"transform":{},"tweenEasing":null}],"name":"right a"},{"frame":[{"duration":24,"transform":{"skX":18.0412,"skY":18.0412},"tweenEasing":0},{"duration":0,"transform":{"skX":18.0412,"skY":18.0412},"tweenEasing":null}],"name":"left a"},{"frame":[{"duration":24,"transform":{},"tweenEasing":null}],"name":"bow"}]},{"duration":24,"frame":[],"slot":[],"ffd":[],"playTimes":0,"name":"hit_assist_1","bone":[{"frame":[{"duration":24,"transform":{},"tweenEasing":0},{"duration":0,"transform":{},"tweenEasing":null}],"name":"root"},{"frame":[{"duration":24,"transform":{"skX":3.4676,"skY":3.4676},"tweenEasing":0},{"duration":0,"transform":{"skX":3.4676,"skY":3.4676},"tweenEasing":null}],"name":"right leg"},{"frame":[{"duration":24,"transform":{"skX":-8.7888,"skY":-8.7888},"tweenEasing":0},{"duration":0,"transform":{"skX":-8.7888,"skY":-8.7888},"tweenEasing":null}],"name":"left leg"},{"frame":[{"duration":5,"transform":{},"tweenEasing":0},{"duration":1,"transform":{"skX":-6.2857,"skY":-6.2857},"tweenEasing":0},{"duration":18,"transform":{"skX":15.3233,"skY":15.3233},"tweenEasing":0},{"duration":0,"transform":{},"tweenEasing":null}],"name":"body"},{"frame":[{"duration":24,"transform":{"skX":-10.859,"skY":-10.859},"tweenEasing":0},{"duration":0,"transform":{"skX":-10.859,"skY":-10.859},"tweenEasing":null}],"name":"right l"},{"frame":[{"duration":24,"transform":{"skX":10.8815,"skY":10.8815},"tweenEasing":0},{"duration":0,"transform":{"skX":10.8815,"skY":10.8815},"tweenEasing":null}],"name":"left l"},{"frame":[{"duration":24,"transform":{},"tweenEasing":null}],"name":"neck"},{"frame":[{"duration":24,"transform":{},"tweenEasing":null}],"name":"shoulder"},{"frame":[{"duration":6,"transform":{"skX":10.0983,"skY":10.0983},"tweenEasing":0},{"duration":6,"transform":{"skX":-47.2641,"skY":-47.2641},"tweenEasing":0},{"duration":6,"transform":{"skX":34.4145,"skY":34.4145},"tweenEasing":0},{"duration":6,"transform":{"skX":-20.5169,"skY":-20.5169},"tweenEasing":0},{"duration":0,"transform":{"skX":10.0983,"skY":10.0983},"tweenEasing":null}],"name":"right arm"},{"frame":[{"duration":24,"transform":{},"tweenEasing":null}],"name":"Head"},{"frame":[{"duration":12,"transform":{},"tweenEasing":0},{"duration":6,"transform":{"skX":-120.598,"skY":-120.598},"tweenEasing":0},{"duration":6,"transform":{"skX":43.068,"skY":43.068},"tweenEasing":0},{"duration":0,"transform":{},"tweenEasing":null}],"name":"left arm"},{"frame":[{"duration":5,"transform":{},"tweenEasing":0},{"duration":1,"transform":{"skX":23.0727,"skY":23.0727},"tweenEasing":0},{"duration":6,"transform":{"skX":21.0873,"skY":21.0873},"tweenEasing":0},{"duration":6,"transform":{"skX":-48.7722,"skY":-48.7722},"tweenEasing":0},{"duration":6,"transform":{"skX":16.8012,"skY":16.8012},"tweenEasing":0},{"duration":0,"transform":{},"tweenEasing":null}],"name":"right a"},{"frame":[{"duration":24,"transform":{"skX":18.0412,"skY":18.0412},"tweenEasing":0},{"duration":0,"transform":{"skX":18.0412,"skY":18.0412},"tweenEasing":null}],"name":"left a"},{"frame":[{"duration":24,"transform":{},"tweenEasing":null}],"name":"bow"}]},{"duration":24,"frame":[],"slot":[],"ffd":[],"playTimes":0,"name":"hit_deal_1","bone":[{"frame":[{"duration":24,"transform":{},"tweenEasing":0},{"duration":0,"transform":{},"tweenEasing":null}],"name":"root"},{"frame":[{"duration":24,"transform":{"skX":3.4676,"skY":3.4676},"tweenEasing":0},{"duration":0,"transform":{"skX":3.4676,"skY":3.4676},"tweenEasing":null}],"name":"right leg"},{"frame":[{"duration":24,"transform":{"skX":-8.7888,"skY":-8.7888},"tweenEasing":0},{"duration":0,"transform":{"skX":-8.7888,"skY":-8.7888},"tweenEasing":null}],"name":"left leg"},{"frame":[{"duration":5,"transform":{},"tweenEasing":0},{"duration":1,"transform":{"skX":-6.2857,"skY":-6.2857},"tweenEasing":0},{"duration":18,"transform":{"skX":15.3233,"skY":15.3233},"tweenEasing":0},{"duration":0,"transform":{},"tweenEasing":null}],"name":"body"},{"frame":[{"duration":24,"transform":{"skX":-10.859,"skY":-10.859},"tweenEasing":0},{"duration":0,"transform":{"skX":-10.859,"skY":-10.859},"tweenEasing":null}],"name":"right l"},{"frame":[{"duration":24,"transform":{"skX":10.8815,"skY":10.8815},"tweenEasing":0},{"duration":0,"transform":{"skX":10.8815,"skY":10.8815},"tweenEasing":null}],"name":"left l"},{"frame":[{"duration":24,"transform":{},"tweenEasing":null}],"name":"neck"},{"frame":[{"duration":24,"transform":{},"tweenEasing":null}],"name":"shoulder"},{"frame":[{"duration":6,"transform":{"skX":10.0983,"skY":10.0983},"tweenEasing":0},{"duration":6,"transform":{"skX":-47.2641,"skY":-47.2641},"tweenEasing":0},{"duration":6,"transform":{"skX":34.4145,"skY":34.4145},"tweenEasing":0},{"duration":6,"transform":{"skX":-20.5169,"skY":-20.5169},"tweenEasing":0},{"duration":0,"transform":{"skX":10.0983,"skY":10.0983},"tweenEasing":null}],"name":"right arm"},{"frame":[{"duration":24,"transform":{},"tweenEasing":null}],"name":"Head"},{"frame":[{"duration":12,"transform":{},"tweenEasing":0},{"duration":6,"transform":{"skX":-120.598,"skY":-120.598},"tweenEasing":0},{"duration":6,"transform":{"skX":43.068,"skY":43.068},"tweenEasing":0},{"duration":0,"transform":{},"tweenEasing":null}],"name":"left arm"},{"frame":[{"duration":5,"transform":{},"tweenEasing":0},{"duration":1,"transform":{"skX":23.0727,"skY":23.0727},"tweenEasing":0},{"duration":6,"transform":{"skX":21.0873,"skY":21.0873},"tweenEasing":0},{"duration":6,"transform":{"skX":-48.7722,"skY":-48.7722},"tweenEasing":0},{"duration":6,"transform":{"skX":16.8012,"skY":16.8012},"tweenEasing":0},{"duration":0,"transform":{},"tweenEasing":null}],"name":"right a"},{"frame":[{"duration":24,"transform":{"skX":18.0412,"skY":18.0412},"tweenEasing":0},{"duration":0,"transform":{"skX":18.0412,"skY":18.0412},"tweenEasing":null}],"name":"left a"},{"frame":[{"duration":24,"transform":{},"tweenEasing":null}],"name":"bow"}]},{"duration":24,"frame":[],"slot":[],"ffd":[],"playTimes":0,"name":"hit_assist_2","bone":[{"frame":[{"duration":24,"transform":{},"tweenEasing":0},{"duration":0,"transform":{},"tweenEasing":null}],"name":"root"},{"frame":[{"duration":24,"transform":{"skX":3.4676,"skY":3.4676},"tweenEasing":0},{"duration":0,"transform":{"skX":3.4676,"skY":3.4676},"tweenEasing":null}],"name":"right leg"},{"frame":[{"duration":24,"transform":{"skX":-8.7888,"skY":-8.7888},"tweenEasing":0},{"duration":0,"transform":{"skX":-8.7888,"skY":-8.7888},"tweenEasing":null}],"name":"left leg"},{"frame":[{"duration":5,"transform":{},"tweenEasing":0},{"duration":1,"transform":{"skX":-6.2857,"skY":-6.2857},"tweenEasing":0},{"duration":18,"transform":{"skX":15.3233,"skY":15.3233},"tweenEasing":0},{"duration":0,"transform":{},"tweenEasing":null}],"name":"body"},{"frame":[{"duration":24,"transform":{"skX":-10.859,"skY":-10.859},"tweenEasing":0},{"duration":0,"transform":{"skX":-10.859,"skY":-10.859},"tweenEasing":null}],"name":"right l"},{"frame":[{"duration":24,"transform":{"skX":10.8815,"skY":10.8815},"tweenEasing":0},{"duration":0,"transform":{"skX":10.8815,"skY":10.8815},"tweenEasing":null}],"name":"left l"},{"frame":[{"duration":24,"transform":{},"tweenEasing":null}],"name":"neck"},{"frame":[{"duration":24,"transform":{},"tweenEasing":null}],"name":"shoulder"},{"frame":[{"duration":6,"transform":{"skX":10.0983,"skY":10.0983},"tweenEasing":0},{"duration":6,"transform":{"skX":-47.2641,"skY":-47.2641},"tweenEasing":0},{"duration":6,"transform":{"skX":34.4145,"skY":34.4145},"tweenEasing":0},{"duration":6,"transform":{"skX":-20.5169,"skY":-20.5169},"tweenEasing":0},{"duration":0,"transform":{"skX":10.0983,"skY":10.0983},"tweenEasing":null}],"name":"right arm"},{"frame":[{"duration":24,"transform":{},"tweenEasing":null}],"name":"Head"},{"frame":[{"duration":12,"transform":{},"tweenEasing":0},{"duration":6,"transform":{"skX":-120.598,"skY":-120.598},"tweenEasing":0},{"duration":6,"transform":{"skX":43.068,"skY":43.068},"tweenEasing":0},{"duration":0,"transform":{},"tweenEasing":null}],"name":"left arm"},{"frame":[{"duration":5,"transform":{},"tweenEasing":0},{"duration":1,"transform":{"skX":23.0727,"skY":23.0727},"tweenEasing":0},{"duration":6,"transform":{"skX":21.0873,"skY":21.0873},"tweenEasing":0},{"duration":6,"transform":{"skX":-48.7722,"skY":-48.7722},"tweenEasing":0},{"duration":6,"transform":{"skX":16.8012,"skY":16.8012},"tweenEasing":0},{"duration":0,"transform":{},"tweenEasing":null}],"name":"right a"},{"frame":[{"duration":24,"transform":{"skX":18.0412,"skY":18.0412},"tweenEasing":0},{"duration":0,"transform":{"skX":18.0412,"skY":18.0412},"tweenEasing":null}],"name":"left a"},{"frame":[{"duration":24,"transform":{},"tweenEasing":null}],"name":"bow"}]},{"duration":24,"frame":[],"slot":[],"ffd":[],"playTimes":0,"name":"hit_deal_2","bone":[{"frame":[{"duration":24,"transform":{},"tweenEasing":0},{"duration":0,"transform":{},"tweenEasing":null}],"name":"root"},{"frame":[{"duration":24,"transform":{"skX":3.4676,"skY":3.4676},"tweenEasing":0},{"duration":0,"transform":{"skX":3.4676,"skY":3.4676},"tweenEasing":null}],"name":"right leg"},{"frame":[{"duration":24,"transform":{"skX":-8.7888,"skY":-8.7888},"tweenEasing":0},{"duration":0,"transform":{"skX":-8.7888,"skY":-8.7888},"tweenEasing":null}],"name":"left leg"},{"frame":[{"duration":5,"transform":{},"tweenEasing":0},{"duration":1,"transform":{"skX":-6.2857,"skY":-6.2857},"tweenEasing":0},{"duration":18,"transform":{"skX":15.3233,"skY":15.3233},"tweenEasing":0},{"duration":0,"transform":{},"tweenEasing":null}],"name":"body"},{"frame":[{"duration":24,"transform":{"skX":-10.859,"skY":-10.859},"tweenEasing":0},{"duration":0,"transform":{"skX":-10.859,"skY":-10.859},"tweenEasing":null}],"name":"right l"},{"frame":[{"duration":24,"transform":{"skX":10.8815,"skY":10.8815},"tweenEasing":0},{"duration":0,"transform":{"skX":10.8815,"skY":10.8815},"tweenEasing":null}],"name":"left l"},{"frame":[{"duration":24,"transform":{},"tweenEasing":null}],"name":"neck"},{"frame":[{"duration":24,"transform":{},"tweenEasing":null}],"name":"shoulder"},{"frame":[{"duration":6,"transform":{"skX":10.0983,"skY":10.0983},"tweenEasing":0},{"duration":6,"transform":{"skX":-47.2641,"skY":-47.2641},"tweenEasing":0},{"duration":6,"transform":{"skX":34.4145,"skY":34.4145},"tweenEasing":0},{"duration":6,"transform":{"skX":-20.5169,"skY":-20.5169},"tweenEasing":0},{"duration":0,"transform":{"skX":10.0983,"skY":10.0983},"tweenEasing":null}],"name":"right arm"},{"frame":[{"duration":24,"transform":{},"tweenEasing":null}],"name":"Head"},{"frame":[{"duration":12,"transform":{},"tweenEasing":0},{"duration":6,"transform":{"skX":-120.598,"skY":-120.598},"tweenEasing":0},{"duration":6,"transform":{"skX":43.068,"skY":43.068},"tweenEasing":0},{"duration":0,"transform":{},"tweenEasing":null}],"name":"left arm"},{"frame":[{"duration":5,"transform":{},"tweenEasing":0},{"duration":1,"transform":{"skX":23.0727,"skY":23.0727},"tweenEasing":0},{"duration":6,"transform":{"skX":21.0873,"skY":21.0873},"tweenEasing":0},{"duration":6,"transform":{"skX":-48.7722,"skY":-48.7722},"tweenEasing":0},{"duration":6,"transform":{"skX":16.8012,"skY":16.8012},"tweenEasing":0},{"duration":0,"transform":{},"tweenEasing":null}],"name":"right a"},{"frame":[{"duration":24,"transform":{"skX":18.0412,"skY":18.0412},"tweenEasing":0},{"duration":0,"transform":{"skX":18.0412,"skY":18.0412},"tweenEasing":null}],"name":"left a"},{"frame":[{"duration":24,"transform":{},"tweenEasing":null}],"name":"bow"}]},{"duration":0,"frame":[],"slot":[],"ffd":[],"playTimes":0,"name":"run_2","bone":[{"frame":[{"duration":0,"transform":{},"tweenEasing":null}],"name":"root"},{"frame":[{"duration":0,"transform":{"skX":22.8671,"skY":22.8671},"tweenEasing":null}],"name":"right leg"},{"frame":[{"duration":0,"transform":{"skX":-27.143,"skY":-27.143},"tweenEasing":null}],"name":"left leg"},{"frame":[{"duration":0,"transform":{},"tweenEasing":null}],"name":"body"},{"frame":[{"duration":0,"transform":{"skX":-22.3748,"skY":-22.3748},"tweenEasing":null}],"name":"right l"},{"frame":[{"duration":0,"transform":{"skX":21.1792,"skY":21.1792},"tweenEasing":null}],"name":"left l"},{"frame":[{"duration":0,"transform":{},"tweenEasing":null}],"name":"neck"},{"frame":[{"duration":0,"transform":{"skX":25.279,"skY":25.279},"tweenEasing":null}],"name":"right arm"},{"frame":[{"duration":0,"transform":{"skX":-25.878,"skY":-25.878},"tweenEasing":null}],"name":"left arm"},{"frame":[{"duration":0,"transform":{},"tweenEasing":null}],"name":"Head"},{"frame":[{"duration":0,"transform":{"skX":16.2686,"skY":16.2686},"tweenEasing":null}],"name":"left a"},{"frame":[{"duration":0,"transform":{"skX":22.918,"skY":22.918},"tweenEasing":null}],"name":"right a"},{"frame":[{"duration":0,"transform":{},"tweenEasing":null}],"name":"bow"},{"frame":[{"duration":0,"transform":{},"tweenEasing":null}],"name":"shoulder"}]},{"duration":0,"frame":[],"slot":[],"ffd":[],"playTimes":0,"name":"fall_1","bone":[{"frame":[{"duration":0,"transform":{},"tweenEasing":null}],"name":"root"},{"frame":[{"duration":0,"transform":{"skX":22.8671,"skY":22.8671},"tweenEasing":null}],"name":"right leg"},{"frame":[{"duration":0,"transform":{"skX":-27.143,"skY":-27.143},"tweenEasing":null}],"name":"left leg"},{"frame":[{"duration":0,"transform":{},"tweenEasing":null}],"name":"body"},{"frame":[{"duration":0,"transform":{"skX":-22.3748,"skY":-22.3748},"tweenEasing":null}],"name":"right l"},{"frame":[{"duration":0,"transform":{"skX":21.1792,"skY":21.1792},"tweenEasing":null}],"name":"left l"},{"frame":[{"duration":0,"transform":{},"tweenEasing":null}],"name":"neck"},{"frame":[{"duration":0,"transform":{"skX":25.279,"skY":25.279},"tweenEasing":null}],"name":"right arm"},{"frame":[{"duration":0,"transform":{"skX":-25.878,"skY":-25.878},"tweenEasing":null}],"name":"left arm"},{"frame":[{"duration":0,"transform":{},"tweenEasing":null}],"name":"Head"},{"frame":[{"duration":0,"transform":{"skX":16.2686,"skY":16.2686},"tweenEasing":null}],"name":"left a"},{"frame":[{"duration":0,"transform":{"skX":22.918,"skY":22.918},"tweenEasing":null}],"name":"right a"},{"frame":[{"duration":0,"transform":{},"tweenEasing":null}],"name":"bow"},{"frame":[{"duration":0,"transform":{},"tweenEasing":null}],"name":"shoulder"}]},{"duration":0,"frame":[],"slot":[],"ffd":[],"playTimes":0,"name":"fall_2","bone":[{"frame":[{"duration":0,"transform":{},"tweenEasing":null}],"name":"root"},{"frame":[{"duration":0,"transform":{"skX":22.8671,"skY":22.8671},"tweenEasing":null}],"name":"right leg"},{"frame":[{"duration":0,"transform":{"skX":-27.143,"skY":-27.143},"tweenEasing":null}],"name":"left leg"},{"frame":[{"duration":0,"transform":{},"tweenEasing":null}],"name":"body"},{"frame":[{"duration":0,"transform":{"skX":-22.3748,"skY":-22.3748},"tweenEasing":null}],"name":"right l"},{"frame":[{"duration":0,"transform":{"skX":21.1792,"skY":21.1792},"tweenEasing":null}],"name":"left l"},{"frame":[{"duration":0,"transform":{},"tweenEasing":null}],"name":"neck"},{"frame":[{"duration":0,"transform":{"skX":25.279,"skY":25.279},"tweenEasing":null}],"name":"right arm"},{"frame":[{"duration":0,"transform":{"skX":-25.878,"skY":-25.878},"tweenEasing":null}],"name":"left arm"},{"frame":[{"duration":0,"transform":{},"tweenEasing":null}],"name":"Head"},{"frame":[{"duration":0,"transform":{"skX":16.2686,"skY":16.2686},"tweenEasing":null}],"name":"left a"},{"frame":[{"duration":0,"transform":{"skX":22.918,"skY":22.918},"tweenEasing":null}],"name":"right a"},{"frame":[{"duration":0,"transform":{},"tweenEasing":null}],"name":"bow"},{"frame":[{"duration":0,"transform":{},"tweenEasing":null}],"name":"shoulder"}]},{"duration":0,"frame":[],"slot":[],"ffd":[],"playTimes":0,"name":"fall_3","bone":[{"frame":[{"duration":0,"transform":{},"tweenEasing":null}],"name":"root"},{"frame":[{"duration":0,"transform":{"skX":22.8671,"skY":22.8671},"tweenEasing":null}],"name":"right leg"},{"frame":[{"duration":0,"transform":{"skX":-27.143,"skY":-27.143},"tweenEasing":null}],"name":"left leg"},{"frame":[{"duration":0,"transform":{},"tweenEasing":null}],"name":"body"},{"frame":[{"duration":0,"transform":{"skX":-22.3748,"skY":-22.3748},"tweenEasing":null}],"name":"right l"},{"frame":[{"duration":0,"transform":{"skX":21.1792,"skY":21.1792},"tweenEasing":null}],"name":"left l"},{"frame":[{"duration":0,"transform":{},"tweenEasing":null}],"name":"neck"},{"frame":[{"duration":0,"transform":{"skX":25.279,"skY":25.279},"tweenEasing":null}],"name":"right arm"},{"frame":[{"duration":0,"transform":{"skX":-25.878,"skY":-25.878},"tweenEasing":null}],"name":"left arm"},{"frame":[{"duration":0,"transform":{},"tweenEasing":null}],"name":"Head"},{"frame":[{"duration":0,"transform":{"skX":16.2686,"skY":16.2686},"tweenEasing":null}],"name":"left a"},{"frame":[{"duration":0,"transform":{"skX":22.918,"skY":22.918},"tweenEasing":null}],"name":"right a"},{"frame":[{"duration":0,"transform":{},"tweenEasing":null}],"name":"bow"},{"frame":[{"duration":0,"transform":{},"tweenEasing":null}],"name":"shoulder"}]},{"duration":0,"frame":[],"slot":[],"ffd":[],"playTimes":0,"name":"death_1","bone":[{"frame":[{"duration":0,"transform":{},"tweenEasing":null}],"name":"root"},{"frame":[{"duration":0,"transform":{"skX":22.8671,"skY":22.8671},"tweenEasing":null}],"name":"right leg"},{"frame":[{"duration":0,"transform":{"skX":-27.143,"skY":-27.143},"tweenEasing":null}],"name":"left leg"},{"frame":[{"duration":0,"transform":{},"tweenEasing":null}],"name":"body"},{"frame":[{"duration":0,"transform":{"skX":-22.3748,"skY":-22.3748},"tweenEasing":null}],"name":"right l"},{"frame":[{"duration":0,"transform":{"skX":21.1792,"skY":21.1792},"tweenEasing":null}],"name":"left l"},{"frame":[{"duration":0,"transform":{},"tweenEasing":null}],"name":"neck"},{"frame":[{"duration":0,"transform":{"skX":25.279,"skY":25.279},"tweenEasing":null}],"name":"right arm"},{"frame":[{"duration":0,"transform":{"skX":-25.878,"skY":-25.878},"tweenEasing":null}],"name":"left arm"},{"frame":[{"duration":0,"transform":{},"tweenEasing":null}],"name":"Head"},{"frame":[{"duration":0,"transform":{"skX":16.2686,"skY":16.2686},"tweenEasing":null}],"name":"left a"},{"frame":[{"duration":0,"transform":{"skX":22.918,"skY":22.918},"tweenEasing":null}],"name":"right a"},{"frame":[{"duration":0,"transform":{},"tweenEasing":null}],"name":"bow"},{"frame":[{"duration":0,"transform":{},"tweenEasing":null}],"name":"shoulder"}]},{"duration":0,"frame":[],"slot":[],"ffd":[],"playTimes":0,"name":"death_2","bone":[{"frame":[{"duration":0,"transform":{},"tweenEasing":null}],"name":"root"},{"frame":[{"duration":0,"transform":{"skX":22.8671,"skY":22.8671},"tweenEasing":null}],"name":"right leg"},{"frame":[{"duration":0,"transform":{"skX":-27.143,"skY":-27.143},"tweenEasing":null}],"name":"left leg"},{"frame":[{"duration":0,"transform":{},"tweenEasing":null}],"name":"body"},{"frame":[{"duration":0,"transform":{"skX":-22.3748,"skY":-22.3748},"tweenEasing":null}],"name":"right l"},{"frame":[{"duration":0,"transform":{"skX":21.1792,"skY":21.1792},"tweenEasing":null}],"name":"left l"},{"frame":[{"duration":0,"transform":{},"tweenEasing":null}],"name":"neck"},{"frame":[{"duration":0,"transform":{"skX":25.279,"skY":25.279},"tweenEasing":null}],"name":"right arm"},{"frame":[{"duration":0,"transform":{"skX":-25.878,"skY":-25.878},"tweenEasing":null}],"name":"left arm"},{"frame":[{"duration":0,"transform":{},"tweenEasing":null}],"name":"Head"},{"frame":[{"duration":0,"transform":{"skX":16.2686,"skY":16.2686},"tweenEasing":null}],"name":"left a"},{"frame":[{"duration":0,"transform":{"skX":22.918,"skY":22.918},"tweenEasing":null}],"name":"right a"},{"frame":[{"duration":0,"transform":{},"tweenEasing":null}],"name":"bow"},{"frame":[{"duration":0,"transform":{},"tweenEasing":null}],"name":"shoulder"}]},{"duration":0,"frame":[],"slot":[],"ffd":[],"playTimes":0,"name":"death_3","bone":[{"frame":[{"duration":0,"transform":{},"tweenEasing":null}],"name":"root"},{"frame":[{"duration":0,"transform":{"skX":22.8671,"skY":22.8671},"tweenEasing":null}],"name":"right leg"},{"frame":[{"duration":0,"transform":{"skX":-27.143,"skY":-27.143},"tweenEasing":null}],"name":"left leg"},{"frame":[{"duration":0,"transform":{},"tweenEasing":null}],"name":"body"},{"frame":[{"duration":0,"transform":{"skX":-22.3748,"skY":-22.3748},"tweenEasing":null}],"name":"right l"},{"frame":[{"duration":0,"transform":{"skX":21.1792,"skY":21.1792},"tweenEasing":null}],"name":"left l"},{"frame":[{"duration":0,"transform":{},"tweenEasing":null}],"name":"neck"},{"frame":[{"duration":0,"transform":{"skX":25.279,"skY":25.279},"tweenEasing":null}],"name":"right arm"},{"frame":[{"duration":0,"transform":{"skX":-25.878,"skY":-25.878},"tweenEasing":null}],"name":"left arm"},{"frame":[{"duration":0,"transform":{},"tweenEasing":null}],"name":"Head"},{"frame":[{"duration":0,"transform":{"skX":16.2686,"skY":16.2686},"tweenEasing":null}],"name":"left a"},{"frame":[{"duration":0,"transform":{"skX":22.918,"skY":22.918},"tweenEasing":null}],"name":"right a"},{"frame":[{"duration":0,"transform":{},"tweenEasing":null}],"name":"bow"},{"frame":[{"duration":0,"transform":{},"tweenEasing":null}],"name":"shoulder"}]},{"duration":6,"frame":[],"slot":[{"frame":[{"duration":6,"color":{},"tweenEasing":null},{"duration":0,"color":{},"tweenEasing":null}],"name":"else4"}],"ffd":[],"playTimes":0,"name":"shot_1","bone":[{"frame":[{"duration":6,"transform":{"y":14.1607,"skX":-10.4096,"skY":-10.4096},"tweenEasing":0},{"duration":0,"transform":{},"tweenEasing":null}],"name":"root"},{"frame":[{"duration":6,"transform":{"skX":18.2795,"skY":18.2795},"tweenEasing":0},{"duration":0,"transform":{"skX":21.275,"skY":21.275},"tweenEasing":null}],"name":"right leg"},{"frame":[{"duration":6,"transform":{"skX":-31.9979,"skY":-31.9979},"tweenEasing":0},{"duration":0,"transform":{"skX":-23.565,"skY":-23.565},"tweenEasing":null}],"name":"right l"},{"frame":[{"duration":6,"transform":{"skX":6.9856,"skY":6.9856},"tweenEasing":0},{"duration":0,"transform":{"skX":21.1234,"skY":21.1234},"tweenEasing":null}],"name":"left l"},{"frame":[{"duration":6,"transform":{"skX":-2.8724,"skY":-2.8724},"tweenEasing":0},{"duration":0,"transform":{"skX":-23.7209,"skY":-23.7209},"tweenEasing":null}],"name":"left leg"},{"frame":[{"duration":6,"transform":{"skX":55.3275,"skY":55.3275},"tweenEasing":0},{"duration":0,"transform":{"skX":-18.3828,"skY":-18.3828},"tweenEasing":null}],"name":"left arm"},{"frame":[{"duration":6,"transform":{},"tweenEasing":null}],"name":"neck"},{"frame":[{"duration":6,"transform":{"skX":-18.2809,"skY":-18.2809},"tweenEasing":0},{"duration":0,"transform":{"skX":1.6126,"skY":1.6126},"tweenEasing":null}],"name":"right arm"},{"frame":[{"duration":6,"transform":{"skX":-60.234,"skY":-60.234},"tweenEasing":0},{"duration":0,"transform":{"skX":65.3671,"skY":65.3671},"tweenEasing":null}],"name":"left a"},{"frame":[{"duration":6,"transform":{},"tweenEasing":null}],"name":"Head"},{"frame":[{"duration":6,"transform":{"skX":17.0065,"skY":17.0065},"tweenEasing":0},{"duration":0,"transform":{},"tweenEasing":null}],"name":"right a"},{"frame":[{"duration":6,"transform":{},"tweenEasing":null}],"name":"body"},{"frame":[{"duration":6,"transform":{"skX":-1.7499,"skY":-1.7499},"tweenEasing":0},{"duration":0,"transform":{},"tweenEasing":null}],"name":"bow"},{"frame":[{"duration":6,"transform":{"skX":-3.2631,"skY":-3.2631},"tweenEasing":0},{"duration":0,"transform":{"skX":23.7207,"skY":23.7207},"tweenEasing":null}],"name":"shoulder"}]}],"skin":[{"name":"","slot":[{"display":[{"type":"image","name":"else","transform":{"y":2.8495,"skX":-91.244,"skY":-91.244,"x":42.4735}}],"name":"else5"},{"display":[{"transform":{},"type":"armature","name":"Bow","filterType":"armature"}],"name":"bow"},{"display":[{"type":"image","name":"else","transform":{"y":-1.0521,"skX":92.2574,"skY":92.2574,"x":31.3321}}],"name":"else1"},{"display":[{"type":"image","name":"else","transform":{"y":1.6359,"skX":87.1107,"skY":87.1107,"x":36.9299}}],"name":"else3"},{"display":[{"type":"image","name":"else","transform":{"y":1.2362,"skX":-89.2077,"skY":-89.2077,"x":37.5706}}],"name":"else6"},{"display":[{"type":"image","name":"else","transform":{"y":0.4491,"skX":-90.8011,"skY":-90.8011,"x":35.8521}}],"name":"else2"},{"display":[{"type":"image","name":"body","transform":{"scX":1.0647,"y":0.031,"scY":1.0647,"skX":89.8584,"skY":89.8584,"x":80.6782}}],"name":"body"},{"display":[{"type":"image","name":"else","transform":{"y":1.1153,"skX":-90.8419,"skY":-90.8419,"x":39.0276}}],"name":"else4"},{"display":[{"type":"image","name":"head","transform":{"skX":-89.1391,"skY":-89.1391}}],"name":"head"},{"display":[{"type":"image","name":"else","transform":{"y":0.4033,"skX":-92.2715,"skY":-92.2715,"x":41.2302}}],"name":"else7"},{"display":[{"transform":{"scX":1.9,"y":-3.3166,"scY":2,"skX":-2.9456,"skY":-2.9456,"x":159.4741},"type":"armature","name":"Arrow","filterType":"armature"}],"name":"arrow"},{"display":[{"type":"image","name":"else","transform":{"y":0.7527,"skX":-90.9863,"skY":-90.9863,"x":37.0989}}],"name":"else"}]}],"type":"Armature","name":"Stickman","defaultActions":[{"gotoAndPlay":"idle_1"}],"slot":[{"name":"body","parent":"body","color":{}},{"z":1,"name":"else","parent":"right arm","color":{}},{"z":2,"name":"else1","parent":"right a","color":{}},{"z":3,"name":"else2","parent":"left arm","color":{}},{"z":4,"name":"else3","parent":"left a","color":{}},{"z":5,"name":"else4","parent":"right leg","color":{}},{"z":6,"name":"else5","parent":"right l","color":{}},{"z":7,"name":"else6","parent":"left l","color":{}},{"z":8,"name":"else7","parent":"left leg","color":{}},{"z":9,"name":"head","parent":"Head","color":{}},{"z":10,"name":"bow","parent":"bow","color":{"gM":0,"bM":0,"rM":0}},{"z":11,"name":"arrow","parent":"left a","color":{}}],"ik":[],"aabb":{"width":350.574463672109,"y":-433.4752409093778,"height":438.3924079538391,"x":-72.65917697951468},"frameRate":24,"bone":[{"name":"root","transform":{"y":-143.9026,"skX":1.1969,"skY":1.1969,"x":-1.2964}},{"length":81,"transform":{"y":-1.5468,"skX":48.1831,"skY":48.1831,"x":0.4956},"parent":"root","name":"right leg"},{"length":77,"transform":{"y":-0.334,"skX":131.0695,"skY":131.0695,"x":-0.7375},"parent":"root","name":"left leg"},{"length":169,"transform":{"y":-0.1233,"skX":-90.235,"skY":-90.235,"x":-1.5328},"parent":"root","name":"body"},{"length":85,"transform":{"y":-1.9027,"skX":42.0446,"skY":42.0446,"x":77.9995},"parent":"right leg","name":"right l"},{"length":81,"transform":{"y":-2.0318,"skX":-37.3661,"skY":-37.3661,"x":78.3474},"parent":"left leg","name":"left l"},{"transform":{"y":-0.0374,"skX":-179.2192,"skY":-179.2192,"x":166.304},"name":"neck","parent":"body"},{"transform":{"y":-2.7749,"x":165.2773},"name":"shoulder","parent":"body"},{"length":78,"transform":{"y":1.453,"skX":126.8093,"skY":126.8093,"x":0.552},"parent":"shoulder","name":"right arm"},{"length":66,"transform":{"y":2.601,"skX":-1.5555,"skY":-1.5555,"x":-63.0863},"parent":"neck","name":"Head"},{"length":79,"transform":{"y":1.5343,"skX":-150.7776,"skY":-150.7776,"x":1.021},"parent":"shoulder","name":"left arm"},{"length":72,"transform":{"skX":-26.5029,"skY":-26.5029,"x":78.1003},"parent":"right arm","name":"right a"},{"length":71,"transform":{"y":-2.1546,"skX":-104.4697,"skY":-104.4697,"x":72.1989},"parent":"left arm","name":"left a"},{"transform":{"y":-0.666,"x":68.7391},"name":"bow","parent":"right a"}]},{"animation":[{"duration":0,"frame":[],"slot":[],"ffd":[],"playTimes":0,"name":"shot","bone":[{"frame":[{"duration":0,"transform":{},"tweenEasing":null}],"name":"root"},{"frame":[{"duration":0,"transform":{},"tweenEasing":null}],"name":"bow"},{"frame":[{"duration":0,"transform":{},"tweenEasing":null}],"name":"top"},{"frame":[{"duration":0,"transform":{},"tweenEasing":null}],"name":"bottom"}]},{"duration":0,"frame":[],"slot":[],"ffd":[],"playTimes":0,"name":"idle","bone":[{"frame":[{"duration":0,"transform":{},"tweenEasing":null}],"name":"root"},{"frame":[{"duration":0,"transform":{},"tweenEasing":null}],"name":"bow"},{"frame":[{"duration":0,"transform":{},"tweenEasing":null}],"name":"top"},{"frame":[{"duration":0,"transform":{},"tweenEasing":null}],"name":"bottom"}]}],"skin":[{"name":"","slot":[{"display":[{"type":"image","name":"standart","transform":{"y":-0.0745,"x":-40.0604}}],"name":"standart"}]}],"type":"Armature","name":"Bow","defaultActions":[{"gotoAndPlay":"idle"}],"slot":[{"name":"standart","parent":"bow","color":{}}],"ik":[],"aabb":{"width":300,"y":-147.66298234775456,"height":300,"x":-189.8104741802988},"frameRate":24,"bone":[{"name":"root","transform":{"y":1.4115,"x":0.25}},{"transform":{"y":1},"name":"bow","parent":"root"},{"transform":{"y":-146.1335,"x":-51.2487},"name":"top","parent":"root"},{"transform":{"y":135.6169,"x":-43.4005},"name":"bottom","parent":"root"}]},{"animation":[{"duration":0,"frame":[],"slot":[],"ffd":[],"playTimes":0,"name":"idle","bone":[{"frame":[{"duration":0,"transform":{},"tweenEasing":null}],"name":"root"},{"frame":[{"duration":0,"transform":{},"tweenEasing":null}],"name":"head"},{"frame":[{"duration":0,"transform":{},"tweenEasing":null}],"name":"tail"}]}],"skin":[{"name":"","slot":[{"display":[{"type":"image","name":"Arrow","transform":{"skX":43.609,"skY":43.609}}],"name":"Arrow"}]}],"type":"Armature","name":"Arrow","defaultActions":[{"gotoAndPlay":"idle"}],"slot":[{"name":"Arrow","parent":"root","color":{}}],"ik":[],"aabb":{"width":100,"y":-50,"height":100,"x":-50},"frameRate":24,"bone":[{"name":"root","transform":{}},{"transform":{"x":57.2526},"name":"head","parent":"root"},{"transform":{"y":-1.1772,"x":-62.7856},"name":"tail","parent":"root"}]},{"animation":[{"duration":0,"frame":[],"slot":[],"ffd":[],"playTimes":0,"name":"animtion0","bone":[{"frame":[{"duration":0,"transform":{},"tweenEasing":null}],"name":"root"}]}],"skin":[{"name":"","slot":[{"display":[{"type":"image","name":"apple","transform":{}}],"name":"apple"}]}],"type":"Armature","name":"Apple","defaultActions":[{"gotoAndPlay":"animtion0"}],"slot":[{"name":"apple","parent":"root","color":{}}],"ik":[],"aabb":{"width":100,"y":-57,"height":114,"x":-50},"frameRate":24,"bone":[{"name":"root","transform":{}}]},{"animation":[{"duration":0,"frame":[],"slot":[],"ffd":[],"playTimes":0,"name":"animtion0","bone":[{"frame":[{"duration":0,"transform":{},"tweenEasing":null}],"name":"root"}]}],"skin":[{"name":"","slot":[{"display":[{"type":"image","name":"butt","transform":{"y":0.0473,"x":0.0473}}],"name":"butt"}]}],"type":"Armature","name":"Butt","defaultActions":[{"gotoAndPlay":"animtion0"}],"slot":[{"name":"butt","parent":"root","color":{}}],"ik":[],"aabb":{"width":300,"y":-149.95265801847205,"height":300,"x":-149.95265801847205},"frameRate":24,"bone":[{"name":"root","transform":{}}]}],"isGlobal":0,"name":"ArcUnlim","version":"4.5"}